{"name":"Snipt Helps Programmers Share Code Snippets","date":1303855259,"url":"http:\/\/blog.programmableweb.com\/2011\/04\/26\/snipt-helps-programmers-share-code-snippets\/","message":"[...] services, including the similarly-named Snipt.org API and Snipplr API. The Geekorium compared snipt.net to snippler back before the API launch: Snipt.net is very pretty. It has a lovely ajaxy interface that swooshes [...]","email":"d41d8cd98f00b204e9800998ecf8427e","_id":"095dd7a0-4334-11e9-bae4-5fe296e4f8b1"}