{"name":"Abhinav Kaiser","date":1149047927,"url":"http:\/\/technopedia.info\/tech","message":"PC is evergreen. It will always be. Things work so beautifully on a PC and a more than 100% compatibility gives us leverage of moving onto any software we wish to use...<br><br>PC is like a Honda, it keeps running as long as there is fuel... Macs are like BMW, very expensive, good looking and needs the most expensive gas and the best of conditions to run...","email":"3289f251b8e68919f37be3fb224241d8","_id":"09b4e810-4334-11e9-99f8-e7c1cb21f2e7"}